[
  {
    "text": "1AM",
    "points": [
      [
        453,
        526
      ],
      [
        479,
        526
      ],
      [
        505,
        526
      ],
      [
        505,
        548
      ],
      [
        479,
        548
      ],
      [
        453,
        548
      ]
    ],
    "isArt": false
  },
  {
    "text": "HOLIDAY",
    "points": [
      [
        416,
        501
      ],
      [
        455,
        501
      ],
      [
        494,
        501
      ],
      [
        494,
        519
      ],
      [
        455,
        519
      ],
      [
        416,
        519
      ]
    ],
    "isArt": true
  },
  {
    "text": "10am",
    "points": [
      [
        345,
        527
      ],
      [
        380,
        527
      ],
      [
        414,
        527
      ],
      [
        414,
        547
      ],
      [
        380,
        547
      ],
      [
        345,
        547
      ]
    ],
    "isArt": false
  },
  {
    "text": "MON",
    "points": [
      [
        380,
        410
      ],
      [
        403,
        410
      ],
      [
        426,
        410
      ],
      [
        426,
        429
      ],
      [
        403,
        429
      ],
      [
        380,
        429
      ]
    ],
    "isArt": false
  },
  {
    "text": "PUBLIC",
    "points": [
      [
        349,
        501
      ],
      [
        382,
        501
      ],
      [
        415,
        501
      ],
      [
        415,
        519
      ],
      [
        382,
        519
      ],
      [
        349,
        519
      ]
    ],
    "isArt": false
  },
  {
    "text": "to",
    "points": [
      [
        416,
        528
      ],
      [
        431,
        528
      ],
      [
        445,
        528
      ],
      [
        445,
        548
      ],
      [
        431,
        548
      ],
      [
        416,
        548
      ]
    ],
    "isArt": false
  },
  {
    "text": "FRI",
    "points": [
      [
        437,
        412
      ],
      [
        453,
        412
      ],
      [
        469,
        412
      ],
      [
        469,
        428
      ],
      [
        453,
        428
      ],
      [
        437,
        428
      ]
    ],
    "isArt": false
  },
  {
    "text": "11AM",
    "points": [
      [
        347,
        435
      ],
      [
        380,
        435
      ],
      [
        413,
        435
      ],
      [
        413,
        458
      ],
      [
        380,
        458
      ],
      [
        347,
        458
      ]
    ],
    "isArt": false
  },
  {
    "text": "OPENING",
    "points": [
      [
        361,
        321
      ],
      [
        389,
        293
      ],
      [
        433,
        279
      ],
      [
        433,
        300
      ],
      [
        403,
        307
      ],
      [
        378,
        334
      ]
    ],
    "isArt": false
  },
  {
    "text": "HOURS",
    "points": [
      [
        444,
        288
      ],
      [
        475,
        303
      ],
      [
        490,
        336
      ],
      [
        480,
        345
      ],
      [
        462,
        318
      ],
      [
        438,
        303
      ]
    ],
    "isArt": true
  },
  {
    "text": "to",
    "points": [
      [
        418,
        439
      ],
      [
        445,
        439
      ],
      [
        447,
        462
      ],
      [
        420,
        462
      ]
    ],
    "isArt": false
  },
  {
    "text": "1AM",
    "points": [
      [
        451,
        439
      ],
      [
        507,
        438
      ],
      [
        504,
        462
      ],
      [
        456,
        463
      ]
    ],
    "isArt": false
  },
  {
    "text": "NON",
    "points": [
      [
        348,
        573
      ],
      [
        403,
        570
      ],
      [
        405,
        597
      ],
      [
        351,
        595
      ]
    ],
    "isArt": false
  },
  {
    "text": "HALAL",
    "points": [
      [
        414,
        571
      ],
      [
        490,
        568
      ],
      [
        496,
        603
      ],
      [
        414,
        600
      ]
    ],
    "isArt": false
  },
  {
    "text": "SAT",
    "points": [
      [
        372,
        486
      ],
      [
        412,
        486
      ],
      [
        414,
        502
      ],
      [
        373,
        504
      ]
    ],
    "isArt": false
  },
  {
    "text": "SUN",
    "points": [
      [
        420,
        486
      ],
      [
        459,
        487
      ],
      [
        459,
        504
      ],
      [
        418,
        502
      ]
    ],
    "isArt": false
  },
  {
    "text": "SMORES",
    "points": [
      [
        385,
        622
      ],
      [
        420,
        612
      ],
      [
        463,
        618
      ],
      [
        463,
        640
      ],
      [
        429,
        634
      ],
      [
        387,
        642
      ]
    ],
    "isArt": false
  }
]