[
  {
    "text": "N\u01a0I",
    "points": [
      [
        183,
        10
      ],
      [
        206,
        10
      ],
      [
        206,
        23
      ],
      [
        183,
        23
      ]
    ],
    "isArt": false
  },
  {
    "text": "\u0110\u1ebeN",
    "points": [
      [
        209,
        7
      ],
      [
        239,
        7
      ],
      [
        239,
        21
      ],
      [
        209,
        21
      ]
    ],
    "isArt": false
  },
  {
    "text": "/",
    "points": [
      [
        239,
        9
      ],
      [
        245,
        9
      ],
      [
        245,
        20
      ],
      [
        239,
        20
      ]
    ],
    "isArt": false
  },
  {
    "text": "TO",
    "points": [
      [
        249,
        8
      ],
      [
        266,
        8
      ],
      [
        266,
        19
      ],
      [
        249,
        19
      ]
    ],
    "isArt": false
  },
  {
    "text": "HANOI",
    "points": [
      [
        189,
        34
      ],
      [
        263,
        34
      ],
      [
        263,
        59
      ],
      [
        189,
        59
      ]
    ],
    "isArt": false
  },
  {
    "text": "GHI",
    "points": [
      [
        181,
        91
      ],
      [
        204,
        91
      ],
      [
        204,
        102
      ],
      [
        181,
        102
      ]
    ],
    "isArt": false
  },
  {
    "text": "CH\u00da",
    "points": [
      [
        209,
        87
      ],
      [
        237,
        87
      ],
      [
        237,
        101
      ],
      [
        209,
        101
      ]
    ],
    "isArt": false
  },
  {
    "text": "/",
    "points": [
      [
        239,
        89
      ],
      [
        245,
        89
      ],
      [
        245,
        100
      ],
      [
        239,
        100
      ]
    ],
    "isArt": false
  },
  {
    "text": "REMARK",
    "points": [
      [
        248,
        87
      ],
      [
        305,
        85
      ],
      [
        306,
        97
      ],
      [
        248,
        100
      ]
    ],
    "isArt": false
  },
  {
    "text": "TKNE",
    "points": [
      [
        188,
        107
      ],
      [
        247,
        104
      ],
      [
        248,
        126
      ],
      [
        189,
        130
      ]
    ],
    "isArt": false
  },
  {
    "text": "0969958887",
    "points": [
      [
        277,
        103
      ],
      [
        427,
        96
      ],
      [
        428,
        120
      ],
      [
        278,
        125
      ]
    ],
    "isArt": false
  }
]