[
  {
    "text": "LAI",
    "points": [
      [
        101,
        127
      ],
      [
        139,
        127
      ],
      [
        137,
        156
      ],
      [
        101,
        156
      ]
    ],
    "isArt": false
  },
  {
    "text": "CH\u00c2U",
    "points": [
      [
        147,
        125
      ],
      [
        208,
        122
      ],
      [
        208,
        154
      ],
      [
        147,
        156
      ]
    ],
    "isArt": false
  },
  {
    "text": "LAI",
    "points": [
      [
        281,
        124
      ],
      [
        322,
        124
      ],
      [
        321,
        154
      ],
      [
        280,
        154
      ]
    ],
    "isArt": false
  },
  {
    "text": "CH\u00c2U",
    "points": [
      [
        327,
        119
      ],
      [
        396,
        118
      ],
      [
        396,
        152
      ],
      [
        326,
        152
      ]
    ],
    "isArt": false
  }
]