[
  {
    "text": "WELCOME",
    "points": [
      [
        162,
        73
      ],
      [
        210,
        36
      ],
      [
        271,
        39
      ],
      [
        273,
        54
      ],
      [
        222,
        65
      ],
      [
        166,
        88
      ]
    ],
    "isArt": true
  },
  {
    "text": "Cole",
    "points": [
      [
        58,
        135
      ],
      [
        159,
        127
      ],
      [
        157,
        175
      ],
      [
        48,
        197
      ]
    ],
    "isArt": true
  },
  {
    "text": "Harbour",
    "points": [
      [
        170,
        114
      ],
      [
        269,
        67
      ],
      [
        403,
        40
      ],
      [
        413,
        80
      ],
      [
        277,
        120
      ],
      [
        170,
        169
      ]
    ],
    "isArt": true
  },
  {
    "text": "HOME",
    "points": [
      [
        97,
        217
      ],
      [
        128,
        211
      ],
      [
        154,
        201
      ],
      [
        156,
        220
      ],
      [
        131,
        229
      ],
      [
        96,
        235
      ]
    ],
    "isArt": false
  },
  {
    "text": "OF",
    "points": [
      [
        157,
        198
      ],
      [
        185,
        187
      ],
      [
        187,
        207
      ],
      [
        159,
        218
      ]
    ],
    "isArt": false
  },
  {
    "text": "SIDNEY",
    "points": [
      [
        187,
        187
      ],
      [
        263,
        156
      ],
      [
        267,
        174
      ],
      [
        189,
        206
      ]
    ],
    "isArt": false
  },
  {
    "text": "CROSBY",
    "points": [
      [
        263,
        153
      ],
      [
        320,
        132
      ],
      [
        357,
        127
      ],
      [
        359,
        144
      ],
      [
        318,
        156
      ],
      [
        271,
        173
      ]
    ],
    "isArt": false
  }
]