[
  {
    "text": "High",
    "points": [
      [
        271,
        95
      ],
      [
        351,
        95
      ],
      [
        351,
        135
      ],
      [
        271,
        135
      ]
    ],
    "isArt": false
  },
  {
    "text": "Fidelity",
    "points": [
      [
        375,
        96
      ],
      [
        517,
        96
      ],
      [
        517,
        137
      ],
      [
        375,
        137
      ]
    ],
    "isArt": false
  },
  {
    "text": "NICK",
    "points": [
      [
        86,
        153
      ],
      [
        349,
        153
      ],
      [
        349,
        247
      ],
      [
        86,
        247
      ]
    ],
    "isArt": true
  },
  {
    "text": "HORNBY",
    "points": [
      [
        76,
        271
      ],
      [
        536,
        271
      ],
      [
        536,
        371
      ],
      [
        76,
        371
      ]
    ],
    "isArt": true
  }
]