[
  {
    "text": "FISH",
    "points": [
      [
        165,
        495
      ],
      [
        105,
        405
      ],
      [
        100,
        312
      ],
      [
        155,
        317
      ],
      [
        162,
        395
      ],
      [
        209,
        458
      ]
    ],
    "isArt": true
  },
  {
    "text": "The",
    "points": [
      [
        122,
        261
      ],
      [
        158,
        218
      ],
      [
        194,
        199
      ],
      [
        215,
        222
      ],
      [
        180,
        252
      ],
      [
        161,
        283
      ]
    ],
    "isArt": true
  },
  {
    "text": "Manhattan",
    "points": [
      [
        219,
        177
      ],
      [
        332,
        171
      ],
      [
        416,
        217
      ],
      [
        454,
        287
      ],
      [
        419,
        305
      ],
      [
        389,
        248
      ],
      [
        315,
        210
      ],
      [
        228,
        218
      ]
    ],
    "isArt": true
  },
  {
    "text": "MARKET",
    "points": [
      [
        220,
        474
      ],
      [
        323,
        482
      ],
      [
        402,
        416
      ],
      [
        415,
        312
      ],
      [
        473,
        318
      ],
      [
        454,
        450
      ],
      [
        350,
        534
      ],
      [
        213,
        530
      ]
    ],
    "isArt": true
  }
]