[
  {
    "text": "L\u01b0u",
    "points": [
      [
        712,
        262
      ],
      [
        734,
        266
      ],
      [
        733,
        281
      ],
      [
        712,
        277
      ]
    ],
    "isArt": false
  },
  {
    "text": "gi\u1eef",
    "points": [
      [
        736,
        267
      ],
      [
        753,
        267
      ],
      [
        752,
        284
      ],
      [
        734,
        283
      ]
    ],
    "isArt": false
  },
  {
    "text": "kho\u1ea3nh",
    "points": [
      [
        704,
        282
      ],
      [
        739,
        285
      ],
      [
        740,
        300
      ],
      [
        703,
        296
      ]
    ],
    "isArt": false
  },
  {
    "text": "kh\u1eafc",
    "points": [
      [
        740,
        286
      ],
      [
        761,
        287
      ],
      [
        761,
        301
      ],
      [
        741,
        300
      ]
    ],
    "isArt": false
  },
  {
    "text": "b\u1ea1n",
    "points": [
      [
        712,
        300
      ],
      [
        737,
        302
      ],
      [
        737,
        321
      ],
      [
        713,
        321
      ]
    ],
    "isArt": false
  },
  {
    "text": "b\u00e8",
    "points": [
      [
        740,
        301
      ],
      [
        756,
        303
      ],
      [
        754,
        320
      ],
      [
        739,
        318
      ]
    ],
    "isArt": false
  },
  {
    "text": "CocaCola",
    "points": [
      [
        743,
        235
      ],
      [
        759,
        235
      ],
      [
        760,
        244
      ],
      [
        744,
        244
      ]
    ],
    "isArt": false
  }
]