[
  {
    "text": "M\u00d4I",
    "points": [
      [
        8,
        5
      ],
      [
        101,
        5
      ],
      [
        101,
        52
      ],
      [
        8,
        52
      ]
    ],
    "isArt": false
  },
  {
    "text": "GI\u1edaI",
    "points": [
      [
        117,
        5
      ],
      [
        218,
        5
      ],
      [
        218,
        48
      ],
      [
        117,
        48
      ]
    ],
    "isArt": false
  },
  {
    "text": "B\u00c1N",
    "points": [
      [
        231,
        7
      ],
      [
        333,
        7
      ],
      [
        333,
        49
      ],
      [
        231,
        49
      ]
    ],
    "isArt": false
  },
  {
    "text": "HO\u1eb6C",
    "points": [
      [
        349,
        6
      ],
      [
        475,
        6
      ],
      [
        475,
        52
      ],
      [
        349,
        52
      ]
    ],
    "isArt": false
  },
  {
    "text": "CHO",
    "points": [
      [
        494,
        7
      ],
      [
        587,
        7
      ],
      [
        587,
        53
      ],
      [
        494,
        53
      ]
    ],
    "isArt": false
  },
  {
    "text": "THU\u00ca",
    "points": [
      [
        602,
        1
      ],
      [
        730,
        1
      ],
      [
        730,
        51
      ],
      [
        602,
        51
      ]
    ],
    "isArt": false
  },
  {
    "text": "T\u01af",
    "points": [
      [
        2,
        63
      ],
      [
        77,
        63
      ],
      [
        77,
        109
      ],
      [
        2,
        109
      ]
    ],
    "isArt": false
  },
  {
    "text": "V\u1ea4N",
    "points": [
      [
        83,
        54
      ],
      [
        177,
        54
      ],
      [
        177,
        108
      ],
      [
        83,
        108
      ]
    ],
    "isArt": false
  },
  {
    "text": "L\u00c0M",
    "points": [
      [
        188,
        62
      ],
      [
        305,
        62
      ],
      [
        305,
        107
      ],
      [
        188,
        107
      ]
    ],
    "isArt": false
  },
  {
    "text": "GI\u1ea4Y",
    "points": [
      [
        314,
        54
      ],
      [
        422,
        54
      ],
      [
        422,
        106
      ],
      [
        314,
        106
      ]
    ],
    "isArt": false
  },
  {
    "text": "T\u1edc",
    "points": [
      [
        438,
        59
      ],
      [
        511,
        59
      ],
      [
        511,
        105
      ],
      [
        438,
        105
      ]
    ],
    "isArt": false
  },
  {
    "text": "NH\u00c0",
    "points": [
      [
        523,
        61
      ],
      [
        624,
        61
      ],
      [
        624,
        105
      ],
      [
        523,
        105
      ]
    ],
    "isArt": false
  },
  {
    "text": "\u0110\u1ea4T",
    "points": [
      [
        641,
        53
      ],
      [
        732,
        53
      ],
      [
        732,
        108
      ],
      [
        641,
        108
      ]
    ],
    "isArt": false
  }
]