[
  {
    "text": "Verbandstoffe",
    "points": [
      [
        1756,
        1294
      ],
      [
        2185,
        1294
      ],
      [
        2185,
        1353
      ],
      [
        1756,
        1353
      ]
    ],
    "isArt": false
  },
  {
    "text": "HEPP",
    "points": [
      [
        1536,
        1297
      ],
      [
        1737,
        1297
      ],
      [
        1737,
        1355
      ],
      [
        1536,
        1355
      ]
    ],
    "isArt": false
  }
]