[
  {
    "text": "ITA",
    "points": [
      [
        25,
        69
      ],
      [
        34,
        30
      ],
      [
        71,
        3
      ],
      [
        101,
        15
      ],
      [
        70,
        43
      ],
      [
        53,
        88
      ]
    ],
    "isArt": true
  },
  {
    "text": "EEN",
    "points": [
      [
        325,
        85
      ],
      [
        340,
        118
      ],
      [
        352,
        166
      ],
      [
        326,
        171
      ],
      [
        322,
        132
      ],
      [
        301,
        94
      ]
    ],
    "isArt": true
  },
  {
    "text": "Rozzis",
    "points": [
      [
        83,
        76
      ],
      [
        334,
        154
      ],
      [
        314,
        223
      ],
      [
        71,
        154
      ]
    ],
    "isArt": true
  },
  {
    "text": "CANTEEN",
    "points": [
      [
        56,
        127
      ],
      [
        97,
        217
      ],
      [
        191,
        289
      ],
      [
        175,
        312
      ],
      [
        70,
        233
      ],
      [
        25,
        138
      ]
    ],
    "isArt": true
  },
  {
    "text": "ITALIAN",
    "points": [
      [
        220,
        289
      ],
      [
        292,
        268
      ],
      [
        329,
        202
      ],
      [
        353,
        213
      ],
      [
        310,
        290
      ],
      [
        227,
        318
      ]
    ],
    "isArt": true
  }
]