[
  {
    "text": "HAPHACO",
    "points": [
      [
        194,
        135
      ],
      [
        443,
        136
      ],
      [
        443,
        184
      ],
      [
        196,
        183
      ]
    ],
    "isArt": false
  },
  {
    "text": "C\u00d4NG",
    "points": [
      [
        82,
        303
      ],
      [
        182,
        304
      ],
      [
        182,
        336
      ],
      [
        82,
        336
      ]
    ],
    "isArt": false
  },
  {
    "text": "TY",
    "points": [
      [
        188,
        307
      ],
      [
        229,
        307
      ],
      [
        223,
        337
      ],
      [
        192,
        335
      ]
    ],
    "isArt": false
  },
  {
    "text": "C\u1ed4",
    "points": [
      [
        239,
        310
      ],
      [
        292,
        294
      ],
      [
        287,
        336
      ],
      [
        241,
        336
      ]
    ],
    "isArt": false
  },
  {
    "text": "PH\u1ea6N",
    "points": [
      [
        299,
        298
      ],
      [
        391,
        298
      ],
      [
        391,
        339
      ],
      [
        299,
        339
      ]
    ],
    "isArt": false
  },
  {
    "text": "H\u00c0",
    "points": [
      [
        399,
        301
      ],
      [
        441,
        300
      ],
      [
        446,
        338
      ],
      [
        400,
        337
      ]
    ],
    "isArt": false
  },
  {
    "text": "ANH",
    "points": [
      [
        463,
        305
      ],
      [
        524,
        305
      ],
      [
        526,
        336
      ],
      [
        454,
        336
      ]
    ],
    "isArt": false
  },
  {
    "text": "PH\u00c1T",
    "points": [
      [
        533,
        300
      ],
      [
        611,
        299
      ],
      [
        610,
        335
      ],
      [
        535,
        335
      ]
    ],
    "isArt": false
  },
  {
    "text": "VPGD:",
    "points": [
      [
        159,
        373
      ],
      [
        224,
        374
      ],
      [
        222,
        396
      ],
      [
        168,
        397
      ]
    ],
    "isArt": false
  },
  {
    "text": "S\u1ed1",
    "points": [
      [
        224,
        370
      ],
      [
        257,
        369
      ],
      [
        251,
        396
      ],
      [
        228,
        395
      ]
    ],
    "isArt": false
  },
  {
    "text": "19",
    "points": [
      [
        259,
        374
      ],
      [
        280,
        374
      ],
      [
        279,
        394
      ],
      [
        261,
        394
      ]
    ],
    "isArt": false
  },
  {
    "text": "/",
    "points": [
      [
        283,
        373
      ],
      [
        288,
        373
      ],
      [
        284,
        396
      ],
      [
        277,
        395
      ]
    ],
    "isArt": false
  },
  {
    "text": "34",
    "points": [
      [
        289,
        374
      ],
      [
        308,
        373
      ],
      [
        308,
        393
      ],
      [
        286,
        394
      ]
    ],
    "isArt": false
  },
  {
    "text": "\u00c2u",
    "points": [
      [
        312,
        370
      ],
      [
        339,
        370
      ],
      [
        337,
        395
      ],
      [
        313,
        395
      ]
    ],
    "isArt": false
  },
  {
    "text": "C\u01a1",
    "points": [
      [
        343,
        374
      ],
      [
        371,
        374
      ],
      [
        370,
        391
      ],
      [
        345,
        393
      ]
    ],
    "isArt": false
  },
  {
    "text": "T\u00e2y",
    "points": [
      [
        385,
        369
      ],
      [
        421,
        369
      ],
      [
        420,
        397
      ],
      [
        390,
        397
      ]
    ],
    "isArt": false
  },
  {
    "text": "H\u1ed3",
    "points": [
      [
        425,
        368
      ],
      [
        455,
        368
      ],
      [
        452,
        393
      ],
      [
        427,
        392
      ]
    ],
    "isArt": false
  },
  {
    "text": "H\u00e0",
    "points": [
      [
        470,
        369
      ],
      [
        496,
        368
      ],
      [
        497,
        391
      ],
      [
        472,
        393
      ]
    ],
    "isArt": false
  },
  {
    "text": "N\u1ed9i",
    "points": [
      [
        502,
        371
      ],
      [
        534,
        370
      ],
      [
        536,
        395
      ],
      [
        502,
        393
      ]
    ],
    "isArt": false
  },
  {
    "text": "\u0110T:",
    "points": [
      [
        172,
        406
      ],
      [
        205,
        406
      ],
      [
        206,
        429
      ],
      [
        173,
        428
      ]
    ],
    "isArt": false
  },
  {
    "text": "04.6.257.1800",
    "points": [
      [
        210,
        407
      ],
      [
        344,
        405
      ],
      [
        340,
        428
      ],
      [
        212,
        428
      ]
    ],
    "isArt": false
  },
  {
    "text": "/",
    "points": [
      [
        345,
        407
      ],
      [
        348,
        407
      ],
      [
        345,
        428
      ],
      [
        340,
        428
      ]
    ],
    "isArt": false
  },
  {
    "text": "Fax:",
    "points": [
      [
        352,
        405
      ],
      [
        391,
        406
      ],
      [
        391,
        426
      ],
      [
        351,
        426
      ]
    ],
    "isArt": false
  },
  {
    "text": "04.6.257.1810",
    "points": [
      [
        394,
        405
      ],
      [
        528,
        401
      ],
      [
        523,
        425
      ],
      [
        397,
        425
      ]
    ],
    "isArt": false
  },
  {
    "text": "Email:",
    "points": [
      [
        61,
        439
      ],
      [
        117,
        440
      ],
      [
        120,
        461
      ],
      [
        64,
        460
      ]
    ],
    "isArt": false
  },
  {
    "text": "haanhphatsteel@gmail.com",
    "points": [
      [
        122,
        440
      ],
      [
        372,
        441
      ],
      [
        370,
        461
      ],
      [
        126,
        462
      ]
    ],
    "isArt": false
  },
  {
    "text": "/",
    "points": [
      [
        377,
        437
      ],
      [
        385,
        437
      ],
      [
        380,
        464
      ],
      [
        375,
        463
      ]
    ],
    "isArt": false
  },
  {
    "text": "Website:",
    "points": [
      [
        388,
        437
      ],
      [
        465,
        436
      ],
      [
        466,
        457
      ],
      [
        391,
        460
      ]
    ],
    "isArt": false
  },
  {
    "text": "http://haphaco.com",
    "points": [
      [
        472,
        438
      ],
      [
        632,
        435
      ],
      [
        632,
        455
      ],
      [
        475,
        458
      ]
    ],
    "isArt": false
  }
]