[
  {
    "text": "GO",
    "points": [
      [
        499,
        148
      ],
      [
        580,
        148
      ],
      [
        649,
        174
      ],
      [
        628,
        270
      ],
      [
        559,
        249
      ],
      [
        503,
        249
      ]
    ],
    "isArt": true
  },
  {
    "text": "BIGELOW",
    "points": [
      [
        493,
        249
      ],
      [
        638,
        264
      ],
      [
        749,
        334
      ],
      [
        736,
        408
      ],
      [
        623,
        343
      ],
      [
        490,
        327
      ]
    ],
    "isArt": true
  },
  {
    "text": "PHARMACY",
    "points": [
      [
        496,
        339
      ],
      [
        748,
        420
      ],
      [
        742,
        496
      ],
      [
        479,
        411
      ]
    ],
    "isArt": true
  },
  {
    "text": "Estab",
    "points": [
      [
        611,
        448
      ],
      [
        713,
        483
      ],
      [
        710,
        513
      ],
      [
        601,
        480
      ]
    ],
    "isArt": true
  },
  {
    "text": "1838",
    "points": [
      [
        608,
        483
      ],
      [
        712,
        511
      ],
      [
        707,
        544
      ],
      [
        595,
        517
      ]
    ],
    "isArt": true
  },
  {
    "text": "PRESCRIPTIONS",
    "points": [
      [
        518,
        531
      ],
      [
        713,
        586
      ],
      [
        712,
        627
      ],
      [
        517,
        558
      ]
    ],
    "isArt": true
  },
  {
    "text": "COSMETICS",
    "points": [
      [
        548,
        574
      ],
      [
        695,
        619
      ],
      [
        694,
        643
      ],
      [
        542,
        606
      ]
    ],
    "isArt": true
  },
  {
    "text": "SURGICAL",
    "points": [
      [
        554,
        615
      ],
      [
        691,
        651
      ],
      [
        691,
        681
      ],
      [
        556,
        646
      ]
    ],
    "isArt": true
  },
  {
    "text": "SUPPLIES",
    "points": [
      [
        557,
        646
      ],
      [
        683,
        676
      ],
      [
        685,
        709
      ],
      [
        550,
        673
      ]
    ],
    "isArt": true
  },
  {
    "text": "HOME",
    "points": [
      [
        547,
        681
      ],
      [
        625,
        699
      ],
      [
        619,
        732
      ],
      [
        539,
        712
      ]
    ],
    "isArt": true
  },
  {
    "text": "CARE",
    "points": [
      [
        628,
        700
      ],
      [
        698,
        721
      ],
      [
        700,
        753
      ],
      [
        628,
        732
      ]
    ],
    "isArt": true
  },
  {
    "text": "FREE",
    "points": [
      [
        589,
        727
      ],
      [
        644,
        739
      ],
      [
        643,
        760
      ],
      [
        589,
        747
      ]
    ],
    "isArt": true
  },
  {
    "text": "DELIVERY",
    "points": [
      [
        568,
        738
      ],
      [
        676,
        766
      ],
      [
        673,
        784
      ],
      [
        562,
        756
      ]
    ],
    "isArt": true
  },
  {
    "text": "533",
    "points": [
      [
        517,
        754
      ],
      [
        602,
        775
      ],
      [
        596,
        817
      ],
      [
        521,
        793
      ]
    ],
    "isArt": true
  },
  {
    "text": "2700",
    "points": [
      [
        622,
        780
      ],
      [
        716,
        805
      ],
      [
        716,
        843
      ],
      [
        614,
        820
      ]
    ],
    "isArt": true
  },
  {
    "text": "orange",
    "points": [
      [
        580,
        879
      ],
      [
        658,
        900
      ],
      [
        652,
        924
      ],
      [
        578,
        906
      ]
    ],
    "isArt": true
  }
]