[
  {
    "text": "H\u00c0",
    "points": [
      [
        189,
        303
      ],
      [
        208,
        303
      ],
      [
        210,
        322
      ],
      [
        189,
        322
      ]
    ],
    "isArt": false
  },
  {
    "text": "N\u1ed8I",
    "points": [
      [
        214,
        303
      ],
      [
        240,
        302
      ],
      [
        239,
        325
      ],
      [
        213,
        326
      ]
    ],
    "isArt": false
  },
  {
    "text": "CH\u00c0O",
    "points": [
      [
        157,
        384
      ],
      [
        277,
        382
      ],
      [
        275,
        430
      ],
      [
        151,
        429
      ]
    ],
    "isArt": false
  },
  {
    "text": "N\u0102M",
    "points": [
      [
        118,
        445
      ],
      [
        214,
        451
      ],
      [
        215,
        496
      ],
      [
        113,
        493
      ]
    ],
    "isArt": false
  },
  {
    "text": "M\u1edaI",
    "points": [
      [
        232,
        447
      ],
      [
        318,
        448
      ],
      [
        315,
        498
      ],
      [
        229,
        496
      ]
    ],
    "isArt": false
  },
  {
    "text": "2016",
    "points": [
      [
        111,
        519
      ],
      [
        339,
        525
      ],
      [
        320,
        607
      ],
      [
        99,
        597
      ]
    ],
    "isArt": false
  }
]