[
  {
    "text": "CROCODILES",
    "points": [
      [
        708,
        599
      ],
      [
        980,
        447
      ],
      [
        1208,
        457
      ],
      [
        1405,
        603
      ],
      [
        1344,
        683
      ],
      [
        1170,
        581
      ],
      [
        956,
        579
      ],
      [
        778,
        697
      ]
    ],
    "isArt": false
  },
  {
    "text": "NO",
    "points": [
      [
        1014,
        1099
      ],
      [
        1102,
        1103
      ],
      [
        1146,
        1079
      ],
      [
        1182,
        1179
      ],
      [
        1088,
        1219
      ],
      [
        990,
        1209
      ]
    ],
    "isArt": false
  },
  {
    "text": "SWIMMING",
    "points": [
      [
        804,
        1145
      ],
      [
        996,
        1225
      ],
      [
        1208,
        1207
      ],
      [
        1364,
        1097
      ],
      [
        1448,
        1173
      ],
      [
        1258,
        1343
      ],
      [
        974,
        1375
      ],
      [
        728,
        1221
      ]
    ],
    "isArt": false
  }
]