[
  {
    "text": "###",
    "points": [
      [
        749,
        241
      ],
      [
        763,
        241
      ],
      [
        764,
        266
      ],
      [
        750,
        266
      ]
    ],
    "isArt": false
  },
  {
    "text": "SEVENTH",
    "points": [
      [
        482,
        353
      ],
      [
        536,
        344
      ],
      [
        537,
        361
      ],
      [
        483,
        370
      ]
    ],
    "isArt": true
  },
  {
    "text": "PUTEH",
    "points": [
      [
        237,
        222
      ],
      [
        290,
        223
      ],
      [
        292,
        241
      ],
      [
        239,
        240
      ]
    ],
    "isArt": false
  },
  {
    "text": "INTO",
    "points": [
      [
        939,
        402
      ],
      [
        984,
        405
      ],
      [
        985,
        433
      ],
      [
        939,
        430
      ]
    ],
    "isArt": true
  },
  {
    "text": "THE",
    "points": [
      [
        983,
        411
      ],
      [
        1017,
        412
      ],
      [
        1017,
        434
      ],
      [
        983,
        434
      ]
    ],
    "isArt": true
  },
  {
    "text": "KACHANG",
    "points": [
      [
        131,
        219
      ],
      [
        235,
        221
      ],
      [
        237,
        240
      ],
      [
        133,
        238
      ]
    ],
    "isArt": false
  },
  {
    "text": "reaL",
    "points": [
      [
        751,
        301
      ],
      [
        768,
        301
      ],
      [
        770,
        356
      ],
      [
        752,
        356
      ]
    ],
    "isArt": true
  },
  {
    "text": "EXIT",
    "points": [
      [
        226,
        22
      ],
      [
        258,
        11
      ],
      [
        263,
        36
      ],
      [
        231,
        47
      ]
    ],
    "isArt": false
  },
  {
    "text": "SON",
    "points": [
      [
        536,
        344
      ],
      [
        563,
        340
      ],
      [
        562,
        357
      ],
      [
        536,
        361
      ]
    ],
    "isArt": true
  },
  {
    "text": "###",
    "points": [
      [
        49,
        223
      ],
      [
        104,
        218
      ],
      [
        105,
        233
      ],
      [
        50,
        238
      ]
    ],
    "isArt": false
  },
  {
    "text": "###",
    "points": [
      [
        61,
        261
      ],
      [
        116,
        256
      ],
      [
        117,
        270
      ],
      [
        61,
        274
      ]
    ],
    "isArt": false
  },
  {
    "text": "###",
    "points": [
      [
        42,
        299
      ],
      [
        82,
        299
      ],
      [
        82,
        307
      ],
      [
        42,
        308
      ]
    ],
    "isArt": false
  },
  {
    "text": "###",
    "points": [
      [
        47,
        338
      ],
      [
        122,
        341
      ],
      [
        121,
        361
      ],
      [
        46,
        358
      ]
    ],
    "isArt": false
  },
  {
    "text": "###",
    "points": [
      [
        64,
        389
      ],
      [
        120,
        395
      ],
      [
        121,
        407
      ],
      [
        64,
        401
      ]
    ],
    "isArt": false
  },
  {
    "text": "###",
    "points": [
      [
        48,
        429
      ],
      [
        113,
        438
      ],
      [
        113,
        452
      ],
      [
        48,
        442
      ]
    ],
    "isArt": false
  },
  {
    "text": "###",
    "points": [
      [
        1016,
        412
      ],
      [
        1056,
        414
      ],
      [
        1064,
        435
      ],
      [
        1017,
        437
      ]
    ],
    "isArt": true
  },
  {
    "text": "###",
    "points": [
      [
        944,
        437
      ],
      [
        1062,
        440
      ],
      [
        1063,
        458
      ],
      [
        940,
        452
      ]
    ],
    "isArt": false
  }
]