[
  {
    "text": "99A-333.33",
    "points": [
      [
        78,
        74
      ],
      [
        604,
        74
      ],
      [
        604,
        176
      ],
      [
        78,
        176
      ]
    ],
    "isArt": false
  },
  {
    "text": "99A",
    "points": [
      [
        240,
        219
      ],
      [
        429,
        219
      ],
      [
        429,
        334
      ],
      [
        240,
        334
      ]
    ],
    "isArt": false
  },
  {
    "text": "333.33",
    "points": [
      [
        173,
        330
      ],
      [
        510,
        330
      ],
      [
        510,
        459
      ],
      [
        173,
        459
      ]
    ],
    "isArt": false
  }
]