[
  {
    "text": "STATE",
    "points": [
      [
        465,
        271
      ],
      [
        494,
        271
      ],
      [
        523,
        271
      ],
      [
        523,
        287
      ],
      [
        494,
        287
      ],
      [
        465,
        287
      ]
    ],
    "isArt": false
  },
  {
    "text": "THE",
    "points": [
      [
        331,
        265
      ],
      [
        350,
        265
      ],
      [
        369,
        265
      ],
      [
        369,
        283
      ],
      [
        350,
        283
      ],
      [
        331,
        283
      ]
    ],
    "isArt": false
  },
  {
    "text": "WELCOME",
    "points": [
      [
        289,
        146
      ],
      [
        341,
        108
      ],
      [
        398,
        123
      ],
      [
        390,
        143
      ],
      [
        345,
        134
      ],
      [
        303,
        159
      ]
    ],
    "isArt": false
  },
  {
    "text": "TO",
    "points": [
      [
        405,
        130
      ],
      [
        424,
        152
      ],
      [
        411,
        166
      ],
      [
        393,
        149
      ]
    ],
    "isArt": false
  },
  {
    "text": "MISS",
    "points": [
      [
        60,
        157
      ],
      [
        327,
        168
      ],
      [
        330,
        318
      ],
      [
        55,
        309
      ]
    ],
    "isArt": true
  },
  {
    "text": "URI",
    "points": [
      [
        409,
        172
      ],
      [
        529,
        177
      ],
      [
        525,
        244
      ],
      [
        407,
        236
      ]
    ],
    "isArt": true
  },
  {
    "text": "SHOW",
    "points": [
      [
        374,
        269
      ],
      [
        430,
        268
      ],
      [
        430,
        288
      ],
      [
        377,
        286
      ]
    ],
    "isArt": false
  },
  {
    "text": "ME",
    "points": [
      [
        439,
        271
      ],
      [
        462,
        271
      ],
      [
        463,
        288
      ],
      [
        436,
        288
      ]
    ],
    "isArt": false
  }
]