[
  {
    "text": "HOPE",
    "points": [
      [
        661,
        128
      ],
      [
        727,
        122
      ],
      [
        731,
        151
      ],
      [
        665,
        155
      ]
    ],
    "isArt": false
  },
  {
    "text": "CLB",
    "points": [
      [
        875,
        101
      ],
      [
        936,
        100
      ],
      [
        937,
        131
      ],
      [
        872,
        132
      ]
    ],
    "isArt": false
  },
  {
    "text": "TN",
    "points": [
      [
        940,
        101
      ],
      [
        991,
        100
      ],
      [
        989,
        129
      ],
      [
        943,
        129
      ]
    ],
    "isArt": false
  },
  {
    "text": "HOPE",
    "points": [
      [
        1013,
        94
      ],
      [
        1105,
        95
      ],
      [
        1103,
        124
      ],
      [
        1014,
        125
      ]
    ],
    "isArt": false
  },
  {
    "text": "L\u00c0O",
    "points": [
      [
        1111,
        85
      ],
      [
        1182,
        84
      ],
      [
        1182,
        122
      ],
      [
        1113,
        125
      ]
    ],
    "isArt": false
  },
  {
    "text": "CAI",
    "points": [
      [
        1192,
        95
      ],
      [
        1249,
        92
      ],
      [
        1251,
        124
      ],
      [
        1192,
        126
      ]
    ],
    "isArt": false
  },
  {
    "text": "\u0110\u00caM",
    "points": [
      [
        787,
        173
      ],
      [
        902,
        172
      ],
      [
        903,
        244
      ],
      [
        783,
        246
      ]
    ],
    "isArt": false
  },
  {
    "text": "NH\u1ea0C",
    "points": [
      [
        918,
        184
      ],
      [
        1072,
        180
      ],
      [
        1076,
        251
      ],
      [
        917,
        256
      ]
    ],
    "isArt": false
  },
  {
    "text": "T\u1eea",
    "points": [
      [
        1082,
        170
      ],
      [
        1169,
        164
      ],
      [
        1167,
        240
      ],
      [
        1083,
        242
      ]
    ],
    "isArt": false
  },
  {
    "text": "THI\u1ec6N",
    "points": [
      [
        1175,
        165
      ],
      [
        1340,
        161
      ],
      [
        1343,
        246
      ],
      [
        1178,
        253
      ]
    ],
    "isArt": false
  },
  {
    "text": "TRAO",
    "points": [
      [
        673,
        308
      ],
      [
        786,
        305
      ],
      [
        781,
        369
      ],
      [
        677,
        368
      ]
    ],
    "isArt": false
  },
  {
    "text": "Y\u00caU",
    "points": [
      [
        788,
        293
      ],
      [
        874,
        292
      ],
      [
        875,
        368
      ],
      [
        795,
        367
      ]
    ],
    "isArt": false
  },
  {
    "text": "TH\u01af\u01a0NG",
    "points": [
      [
        882,
        296
      ],
      [
        1053,
        288
      ],
      [
        1056,
        360
      ],
      [
        889,
        365
      ]
    ],
    "isArt": false
  },
  {
    "text": "TRAO",
    "points": [
      [
        1059,
        298
      ],
      [
        1170,
        298
      ],
      [
        1175,
        361
      ],
      [
        1067,
        361
      ]
    ],
    "isArt": false
  },
  {
    "text": "C\u1ea2",
    "points": [
      [
        1180,
        273
      ],
      [
        1244,
        271
      ],
      [
        1244,
        359
      ],
      [
        1187,
        359
      ]
    ],
    "isArt": false
  },
  {
    "text": "T\u1ea4M",
    "points": [
      [
        1247,
        276
      ],
      [
        1346,
        277
      ],
      [
        1346,
        356
      ],
      [
        1258,
        356
      ]
    ],
    "isArt": false
  },
  {
    "text": "L\u00d2NG",
    "points": [
      [
        1353,
        278
      ],
      [
        1463,
        278
      ],
      [
        1472,
        353
      ],
      [
        1354,
        357
      ]
    ],
    "isArt": false
  },
  {
    "text": "L\u00e0o",
    "points": [
      [
        1148,
        379
      ],
      [
        1192,
        381
      ],
      [
        1190,
        417
      ],
      [
        1149,
        417
      ]
    ],
    "isArt": false
  },
  {
    "text": "Cai",
    "points": [
      [
        1192,
        380
      ],
      [
        1230,
        382
      ],
      [
        1226,
        415
      ],
      [
        1194,
        412
      ]
    ],
    "isArt": false
  },
  {
    "text": "ng\u00e0y",
    "points": [
      [
        1230,
        384
      ],
      [
        1281,
        384
      ],
      [
        1274,
        417
      ],
      [
        1229,
        417
      ]
    ],
    "isArt": false
  },
  {
    "text": "12",
    "points": [
      [
        1285,
        384
      ],
      [
        1308,
        386
      ],
      [
        1306,
        411
      ],
      [
        1284,
        412
      ]
    ],
    "isArt": false
  },
  {
    "text": "th\u00e1ng",
    "points": [
      [
        1313,
        383
      ],
      [
        1369,
        384
      ],
      [
        1367,
        417
      ],
      [
        1311,
        417
      ]
    ],
    "isArt": false
  },
  {
    "text": "9",
    "points": [
      [
        1371,
        383
      ],
      [
        1384,
        383
      ],
      [
        1380,
        410
      ],
      [
        1366,
        410
      ]
    ],
    "isArt": false
  },
  {
    "text": "n\u0103m",
    "points": [
      [
        1388,
        384
      ],
      [
        1431,
        384
      ],
      [
        1429,
        412
      ],
      [
        1386,
        411
      ]
    ],
    "isArt": false
  },
  {
    "text": "2015",
    "points": [
      [
        1431,
        384
      ],
      [
        1482,
        381
      ],
      [
        1483,
        410
      ],
      [
        1432,
        410
      ]
    ],
    "isArt": false
  },
  {
    "text": "HOPE",
    "points": [
      [
        1119,
        600
      ],
      [
        1144,
        603
      ],
      [
        1142,
        611
      ],
      [
        1116,
        607
      ]
    ],
    "isArt": false
  }
]