[
  {
    "text": "C\u1ed4NG",
    "points": [
      [
        12,
        232
      ],
      [
        66,
        232
      ],
      [
        66,
        285
      ],
      [
        12,
        285
      ]
    ],
    "isArt": false
  },
  {
    "text": "TR\u01af\u1edcNG",
    "points": [
      [
        70,
        236
      ],
      [
        141,
        236
      ],
      [
        141,
        289
      ],
      [
        70,
        289
      ]
    ],
    "isArt": false
  },
  {
    "text": "AN",
    "points": [
      [
        144,
        240
      ],
      [
        170,
        240
      ],
      [
        170,
        290
      ],
      [
        144,
        290
      ]
    ],
    "isArt": false
  },
  {
    "text": "TO\u00c0N",
    "points": [
      [
        175,
        243
      ],
      [
        218,
        243
      ],
      [
        218,
        293
      ],
      [
        175,
        293
      ]
    ],
    "isArt": false
  },
  {
    "text": "GIAO",
    "points": [
      [
        221,
        246
      ],
      [
        261,
        246
      ],
      [
        261,
        296
      ],
      [
        221,
        296
      ]
    ],
    "isArt": false
  },
  {
    "text": "TH\u00d4NG",
    "points": [
      [
        265,
        247
      ],
      [
        315,
        247
      ],
      [
        315,
        296
      ],
      [
        265,
        296
      ]
    ],
    "isArt": false
  },
  {
    "text": "\u0110\u1ed8I",
    "points": [
      [
        79,
        204
      ],
      [
        103,
        204
      ],
      [
        103,
        221
      ],
      [
        79,
        221
      ]
    ],
    "isArt": false
  },
  {
    "text": "NI\u00caN",
    "points": [
      [
        139,
        210
      ],
      [
        167,
        210
      ],
      [
        167,
        224
      ],
      [
        139,
        224
      ]
    ],
    "isArt": false
  },
  {
    "text": "PHONG",
    "points": [
      [
        196,
        210
      ],
      [
        233,
        210
      ],
      [
        233,
        226
      ],
      [
        196,
        226
      ]
    ],
    "isArt": false
  },
  {
    "text": "CH\u00cd",
    "points": [
      [
        251,
        215
      ],
      [
        270,
        215
      ],
      [
        270,
        231
      ],
      [
        251,
        231
      ]
    ],
    "isArt": false
  },
  {
    "text": "\u0110\u1ed8I",
    "points": [
      [
        100,
        220
      ],
      [
        125,
        220
      ],
      [
        125,
        235
      ],
      [
        100,
        235
      ]
    ],
    "isArt": false
  },
  {
    "text": "TRUNG",
    "points": [
      [
        172,
        224
      ],
      [
        208,
        224
      ],
      [
        208,
        242
      ],
      [
        172,
        242
      ]
    ],
    "isArt": false
  },
  {
    "text": "C\u01a0",
    "points": [
      [
        232,
        228
      ],
      [
        250,
        228
      ],
      [
        250,
        246
      ],
      [
        232,
        246
      ]
    ],
    "isArt": false
  },
  {
    "text": "THI\u1ebeU",
    "points": [
      [
        104,
        203
      ],
      [
        138,
        203
      ],
      [
        138,
        220
      ],
      [
        104,
        220
      ]
    ],
    "isArt": false
  },
  {
    "text": "TI\u1ec0N",
    "points": [
      [
        170,
        204
      ],
      [
        197,
        204
      ],
      [
        197,
        228
      ],
      [
        170,
        228
      ]
    ],
    "isArt": false
  },
  {
    "text": "H\u1ed2",
    "points": [
      [
        232,
        211
      ],
      [
        252,
        211
      ],
      [
        252,
        230
      ],
      [
        232,
        230
      ]
    ],
    "isArt": false
  },
  {
    "text": "MINH",
    "points": [
      [
        271,
        217
      ],
      [
        302,
        217
      ],
      [
        302,
        233
      ],
      [
        271,
        233
      ]
    ],
    "isArt": false
  },
  {
    "text": "LI\u00caN",
    "points": [
      [
        74,
        218
      ],
      [
        101,
        218
      ],
      [
        101,
        236
      ],
      [
        74,
        236
      ]
    ],
    "isArt": false
  },
  {
    "text": "TR\u01af\u1edcNG",
    "points": [
      [
        126,
        223
      ],
      [
        171,
        223
      ],
      [
        171,
        238
      ],
      [
        126,
        238
      ]
    ],
    "isArt": false
  },
  {
    "text": "H\u1eccC",
    "points": [
      [
        210,
        224
      ],
      [
        233,
        224
      ],
      [
        233,
        245
      ],
      [
        210,
        245
      ]
    ],
    "isArt": false
  },
  {
    "text": "S\u1ede",
    "points": [
      [
        250,
        229
      ],
      [
        265,
        229
      ],
      [
        265,
        243
      ],
      [
        250,
        243
      ]
    ],
    "isArt": false
  },
  {
    "text": "\u0110\u1ed6",
    "points": [
      [
        266,
        230
      ],
      [
        283,
        230
      ],
      [
        283,
        245
      ],
      [
        266,
        245
      ]
    ],
    "isArt": false
  },
  {
    "text": "S\u01a0N",
    "points": [
      [
        281,
        233
      ],
      [
        305,
        233
      ],
      [
        305,
        246
      ],
      [
        281,
        246
      ]
    ],
    "isArt": false
  }
]