[
  {
    "text": "VI\u1eb8T",
    "points": [
      [
        152,
        195
      ],
      [
        275,
        187
      ],
      [
        265,
        233
      ],
      [
        168,
        240
      ]
    ],
    "isArt": false
  },
  {
    "text": "NAM",
    "points": [
      [
        291,
        187
      ],
      [
        402,
        181
      ],
      [
        396,
        224
      ],
      [
        287,
        223
      ]
    ],
    "isArt": false
  },
  {
    "text": "NAM",
    "points": [
      [
        61,
        341
      ],
      [
        73,
        338
      ],
      [
        73,
        347
      ],
      [
        63,
        349
      ]
    ],
    "isArt": false
  },
  {
    "text": "V\u00d4",
    "points": [
      [
        74,
        338
      ],
      [
        81,
        338
      ],
      [
        82,
        347
      ],
      [
        74,
        347
      ]
    ],
    "isArt": false
  },
  {
    "text": "CHIEN",
    "points": [
      [
        305,
        291
      ],
      [
        323,
        298
      ],
      [
        320,
        305
      ],
      [
        301,
        298
      ]
    ],
    "isArt": false
  },
  {
    "text": "I",
    "points": [
      [
        380,
        127
      ],
      [
        391,
        130
      ],
      [
        390,
        153
      ],
      [
        378,
        151
      ]
    ],
    "isArt": false
  },
  {
    "text": "VIET",
    "points": [
      [
        246,
        292
      ],
      [
        273,
        299
      ],
      [
        271,
        309
      ],
      [
        247,
        300
      ]
    ],
    "isArt": false
  },
  {
    "text": "NA",
    "points": [
      [
        1,
        255
      ],
      [
        15,
        257
      ],
      [
        17,
        269
      ],
      [
        1,
        266
      ]
    ],
    "isArt": false
  }
]