[
  {
    "text": "T",
    "points": [
      [
        31,
        18
      ],
      [
        48,
        14
      ],
      [
        48,
        28
      ],
      [
        30,
        33
      ]
    ],
    "isArt": false
  },
  {
    "text": "Y",
    "points": [
      [
        83,
        6
      ],
      [
        96,
        4
      ],
      [
        95,
        15
      ],
      [
        83,
        18
      ]
    ],
    "isArt": false
  },
  {
    "text": "F",
    "points": [
      [
        1,
        58
      ],
      [
        12,
        55
      ],
      [
        11,
        66
      ],
      [
        1,
        69
      ]
    ],
    "isArt": false
  },
  {
    "text": "G",
    "points": [
      [
        49,
        44
      ],
      [
        66,
        39
      ],
      [
        66,
        52
      ],
      [
        53,
        55
      ]
    ],
    "isArt": false
  },
  {
    "text": "H",
    "points": [
      [
        99,
        32
      ],
      [
        118,
        28
      ],
      [
        117,
        38
      ],
      [
        101,
        42
      ]
    ],
    "isArt": false
  },
  {
    "text": "J",
    "points": [
      [
        152,
        19
      ],
      [
        166,
        15
      ],
      [
        167,
        27
      ],
      [
        156,
        30
      ]
    ],
    "isArt": false
  },
  {
    "text": "K",
    "points": [
      [
        200,
        5
      ],
      [
        217,
        2
      ],
      [
        218,
        14
      ],
      [
        202,
        18
      ]
    ],
    "isArt": false
  },
  {
    "text": "V",
    "points": [
      [
        28,
        80
      ],
      [
        43,
        77
      ],
      [
        41,
        90
      ],
      [
        33,
        91
      ]
    ],
    "isArt": false
  },
  {
    "text": "B",
    "points": [
      [
        85,
        67
      ],
      [
        95,
        64
      ],
      [
        97,
        74
      ],
      [
        88,
        78
      ]
    ],
    "isArt": false
  },
  {
    "text": "N",
    "points": [
      [
        135,
        53
      ],
      [
        149,
        51
      ],
      [
        151,
        61
      ],
      [
        138,
        66
      ]
    ],
    "isArt": false
  },
  {
    "text": "M",
    "points": [
      [
        186,
        40
      ],
      [
        203,
        37
      ],
      [
        207,
        49
      ],
      [
        187,
        53
      ]
    ],
    "isArt": false
  },
  {
    "text": "COFFEE",
    "points": [
      [
        796,
        135
      ],
      [
        860,
        143
      ],
      [
        879,
        168
      ],
      [
        788,
        164
      ]
    ],
    "isArt": false
  },
  {
    "text": "shipping",
    "points": [
      [
        775,
        226
      ],
      [
        798,
        257
      ],
      [
        795,
        268
      ],
      [
        764,
        231
      ]
    ],
    "isArt": false
  },
  {
    "text": "0886550560",
    "points": [
      [
        799,
        256
      ],
      [
        892,
        273
      ],
      [
        887,
        291
      ],
      [
        795,
        273
      ]
    ],
    "isArt": false
  },
  {
    "text": "Nhi\u1ec1u",
    "points": [
      [
        307,
        167
      ],
      [
        357,
        156
      ],
      [
        363,
        166
      ],
      [
        315,
        182
      ]
    ],
    "isArt": false
  },
  {
    "text": "t\u00e1c",
    "points": [
      [
        357,
        155
      ],
      [
        381,
        147
      ],
      [
        387,
        158
      ],
      [
        364,
        167
      ]
    ],
    "isArt": false
  },
  {
    "text": "gi\u1ea3",
    "points": [
      [
        383,
        147
      ],
      [
        408,
        139
      ],
      [
        414,
        152
      ],
      [
        388,
        162
      ]
    ],
    "isArt": true
  },
  {
    "text": "t\u1eadp",
    "points": [
      [
        438,
        376
      ],
      [
        456,
        369
      ],
      [
        460,
        378
      ],
      [
        442,
        386
      ]
    ],
    "isArt": true
  },
  {
    "text": "truy\u1ec7n",
    "points": [
      [
        457,
        369
      ],
      [
        485,
        360
      ],
      [
        489,
        368
      ],
      [
        460,
        378
      ]
    ],
    "isArt": true
  },
  {
    "text": "ng\u1eafn",
    "points": [
      [
        486,
        360
      ],
      [
        509,
        350
      ],
      [
        514,
        358
      ],
      [
        491,
        369
      ]
    ],
    "isArt": true
  },
  {
    "text": "Khi",
    "points": [
      [
        374,
        446
      ],
      [
        499,
        394
      ],
      [
        522,
        451
      ],
      [
        417,
        535
      ]
    ],
    "isArt": true
  },
  {
    "text": "tr\u00e1i",
    "points": [
      [
        470,
        473
      ],
      [
        553,
        434
      ],
      [
        565,
        479
      ],
      [
        486,
        510
      ]
    ],
    "isArt": false
  },
  {
    "text": "tim",
    "points": [
      [
        555,
        447
      ],
      [
        624,
        426
      ],
      [
        629,
        469
      ],
      [
        560,
        490
      ]
    ],
    "isArt": false
  },
  {
    "text": "l\u1ed7i",
    "points": [
      [
        537,
        474
      ],
      [
        618,
        491
      ],
      [
        607,
        522
      ],
      [
        538,
        553
      ]
    ],
    "isArt": false
  },
  {
    "text": "nh\u1ecbp",
    "points": [
      [
        571,
        512
      ],
      [
        656,
        482
      ],
      [
        669,
        554
      ],
      [
        583,
        559
      ]
    ],
    "isArt": false
  },
  {
    "text": "h\u1ea3i",
    "points": [
      [
        534,
        608
      ],
      [
        548,
        602
      ],
      [
        553,
        613
      ],
      [
        538,
        619
      ]
    ],
    "isArt": false
  },
  {
    "text": "\u0111\u0103ng",
    "points": [
      [
        549,
        601
      ],
      [
        574,
        592
      ],
      [
        579,
        603
      ],
      [
        555,
        613
      ]
    ],
    "isArt": false
  }
]