[
  {
    "text": "PH\u00d3",
    "points": [
      [
        194,
        206
      ],
      [
        318,
        206
      ],
      [
        318,
        258
      ],
      [
        194,
        258
      ]
    ],
    "isArt": false
  },
  {
    "text": "HI\u1ec6U",
    "points": [
      [
        333,
        208
      ],
      [
        479,
        208
      ],
      [
        479,
        266
      ],
      [
        333,
        266
      ]
    ],
    "isArt": false
  },
  {
    "text": "TR\u01af\u1edeNG",
    "points": [
      [
        490,
        210
      ],
      [
        739,
        210
      ],
      [
        739,
        261
      ],
      [
        490,
        261
      ]
    ],
    "isArt": false
  },
  {
    "text": "Vice",
    "points": [
      [
        316,
        284
      ],
      [
        438,
        284
      ],
      [
        438,
        328
      ],
      [
        316,
        328
      ]
    ],
    "isArt": false
  },
  {
    "text": "Rector",
    "points": [
      [
        448,
        283
      ],
      [
        606,
        283
      ],
      [
        606,
        328
      ],
      [
        448,
        328
      ]
    ],
    "isArt": false
  }
]