[
  {
    "text": "THAILAND",
    "points": [
      [
        324,
        588
      ],
      [
        383,
        606
      ],
      [
        443,
        589
      ],
      [
        451,
        613
      ],
      [
        379,
        638
      ],
      [
        310,
        625
      ]
    ],
    "isArt": true
  },
  {
    "text": "Hat",
    "points": [
      [
        226,
        667
      ],
      [
        260,
        709
      ],
      [
        290,
        720
      ],
      [
        267,
        768
      ],
      [
        229,
        753
      ],
      [
        186,
        703
      ]
    ],
    "isArt": true
  },
  {
    "text": "Yai",
    "points": [
      [
        297,
        719
      ],
      [
        335,
        738
      ],
      [
        362,
        738
      ],
      [
        365,
        789
      ],
      [
        319,
        794
      ],
      [
        280,
        772
      ]
    ],
    "isArt": true
  },
  {
    "text": "Thailand",
    "points": [
      [
        380,
        733
      ],
      [
        462,
        708
      ],
      [
        523,
        636
      ],
      [
        575,
        662
      ],
      [
        495,
        756
      ],
      [
        389,
        791
      ]
    ],
    "isArt": true
  }
]