[
  {
    "text": "e",
    "points": [
      [
        196,
        224
      ],
      [
        257,
        224
      ],
      [
        257,
        279
      ],
      [
        196,
        279
      ]
    ],
    "isArt": false
  },
  {
    "text": "g",
    "points": [
      [
        196,
        294
      ],
      [
        262,
        294
      ],
      [
        262,
        370
      ],
      [
        196,
        370
      ]
    ],
    "isArt": false
  },
  {
    "text": "intelligent",
    "points": [
      [
        23,
        422
      ],
      [
        226,
        422
      ],
      [
        226,
        461
      ],
      [
        23,
        461
      ]
    ],
    "isArt": false
  },
  {
    "text": "inhabited",
    "points": [
      [
        245,
        423
      ],
      [
        444,
        423
      ],
      [
        444,
        454
      ],
      [
        245,
        454
      ]
    ],
    "isArt": false
  },
  {
    "text": "environments",
    "points": [
      [
        25,
        457
      ],
      [
        303,
        457
      ],
      [
        303,
        490
      ],
      [
        25,
        490
      ]
    ],
    "isArt": false
  },
  {
    "text": "group",
    "points": [
      [
        323,
        469
      ],
      [
        445,
        469
      ],
      [
        445,
        499
      ],
      [
        323,
        499
      ]
    ],
    "isArt": false
  },
  {
    "text": "University",
    "points": [
      [
        27,
        513
      ],
      [
        244,
        513
      ],
      [
        244,
        554
      ],
      [
        27,
        554
      ]
    ],
    "isArt": false
  },
  {
    "text": "of",
    "points": [
      [
        264,
        516
      ],
      [
        306,
        516
      ],
      [
        306,
        546
      ],
      [
        264,
        546
      ]
    ],
    "isArt": false
  },
  {
    "text": "Essex",
    "points": [
      [
        321,
        518
      ],
      [
        442,
        518
      ],
      [
        442,
        548
      ],
      [
        321,
        548
      ]
    ],
    "isArt": false
  }
]