[
  {
    "text": "PAUL",
    "points": [
      [
        259,
        542
      ],
      [
        313,
        462
      ],
      [
        390,
        410
      ],
      [
        425,
        458
      ],
      [
        354,
        507
      ],
      [
        307,
        576
      ]
    ],
    "isArt": true
  },
  {
    "text": "&",
    "points": [
      [
        409,
        405
      ],
      [
        474,
        387
      ],
      [
        487,
        447
      ],
      [
        430,
        461
      ]
    ],
    "isArt": true
  },
  {
    "text": "SHARK",
    "points": [
      [
        492,
        387
      ],
      [
        637,
        409
      ],
      [
        756,
        521
      ],
      [
        708,
        564
      ],
      [
        604,
        471
      ],
      [
        485,
        446
      ]
    ],
    "isArt": true
  },
  {
    "text": "yachting",
    "points": [
      [
        305,
        660
      ],
      [
        701,
        638
      ],
      [
        654,
        761
      ],
      [
        280,
        780
      ]
    ],
    "isArt": true
  }
]