[
  {
    "text": "WELCOME",
    "points": [
      [
        878,
        854
      ],
      [
        1181,
        773
      ],
      [
        1499,
        818
      ],
      [
        1507,
        950
      ],
      [
        1190,
        896
      ],
      [
        893,
        958
      ]
    ],
    "isArt": false
  },
  {
    "text": "TO",
    "points": [
      [
        1127,
        941
      ],
      [
        1239,
        931
      ],
      [
        1242,
        1018
      ],
      [
        1134,
        1024
      ]
    ],
    "isArt": false
  },
  {
    "text": "MUDVILLE",
    "points": [
      [
        848,
        1064
      ],
      [
        1568,
        1034
      ],
      [
        1574,
        1148
      ],
      [
        848,
        1172
      ]
    ],
    "isArt": false
  },
  {
    "text": "POPULATION",
    "points": [
      [
        869,
        1229
      ],
      [
        1367,
        1205
      ],
      [
        1364,
        1274
      ],
      [
        869,
        1298
      ]
    ],
    "isArt": false
  },
  {
    "text": "352",
    "points": [
      [
        1397,
        1208
      ],
      [
        1502,
        1202
      ],
      [
        1505,
        1275
      ],
      [
        1388,
        1280
      ]
    ],
    "isArt": false
  }
]